sypy/__init__.py
sypy/_logging.py
sypy/_packet.py
sypy/_utils.py
sypy/parameters.py
sypy/_dispatcher/__init__.py
sypy/_dispatcher/callback.py
sypy/http/__init__.py
sypy/http/_errors.py
sypy/http/_method.py
sypy/http/_status.py
sypy/http/_frames/__init__.py
sypy/http/_frames/parts.py
sypy/http/path/__init__.py
sypy/http/path/characters.py
sypy/http/path/encoder.py
sypy-0.0.2.dist-info/METADATA
sypy-0.0.2.dist-info/WHEEL
sypy-0.0.2.dist-info/license.txt
sypy-0.0.2.dist-info/top_level.txt
sypy-0.0.2.dist-info/RECORD
