Metadata-Version: 2.1
Name: sypy
Version: 0.0.2
Summary: fastapi rip-off
Author-email: "Ivan \"Spaceginner\"" <ivan.demian2009@gmail.com>
License: sypy - python http api server
Project-URL: Homepage, https://github.com/Spaceginner/sypy
Project-URL: Bug Tracker, https://github.com/Spaceginner/sypy/issues
Classifier: Development Status :: 3 - Alpha
Classifier: Environment :: Web Environment
Classifier: Intended Audience :: Developers
Classifier: License :: OSI Approved :: GNU General Public License v2 (GPLv2)
Classifier: Natural Language :: English
Classifier: Operating System :: OS Independent
Classifier: Programming Language :: Python :: 3.12
Classifier: Topic :: Internet :: WWW/HTTP :: HTTP Servers
Classifier: Topic :: Software Development :: Libraries :: Application Frameworks
Classifier: Typing :: Typed
Requires-Python: >=3.12
License-File: license.txt
